ics/__init__.py
ics/__meta__.py
ics/attendee.py
ics/component.py
ics/event.py
ics/icalendar.py
ics/timeline.py
ics/todo.py
ics/tools.py
ics/types.py
ics/utils.py
ics/alarm/__init__.py
ics/alarm/audio.py
ics/alarm/base.py
ics/alarm/custom.py
ics/alarm/display.py
ics/alarm/email.py
ics/alarm/none.py
ics/alarm/utils.py
ics/grammar/__init__.py
ics/grammar/contentline.ebnf
ics/grammar/contentline.py
ics/grammar/parse.py
ics/parsers/alarm_parser.py
ics/parsers/attendee_parser.py
ics/parsers/event_parser.py
ics/parsers/icalendar_parser.py
ics/parsers/parser.py
ics/parsers/todo_parser.py
ics/serializers/alarm_serializer.py
ics/serializers/attendee_serializer.py
ics/serializers/event_serializer.py
ics/serializers/icalendar_serializer.py
ics/serializers/serializer.py
ics/serializers/todo_serializer.py
ics-0.7.2.dist-info/LICENSE.rst
ics-0.7.2.dist-info/METADATA
ics-0.7.2.dist-info/WHEEL
ics-0.7.2.dist-info/top_level.txt
ics-0.7.2.dist-info/RECORD
