Metadata-Version: 2.1
Name: ics
Version: 0.7.2
Summary: Python icalendar (rfc5545) parser
Home-page: http://github.com/C4ptainCrunch/ics.py
Author: Nikita Marchant
Author-email: nikita.marchant@gmail.com
License: Apache License, Version 2.0
Keywords: ics icalendar calendar event todo rfc5545 parser pythonic
Classifier: Development Status :: 4 - Beta
Classifier: Topic :: Software Development :: Libraries
Classifier: Topic :: Software Development :: Libraries :: Python Modules
Classifier: Intended Audience :: Developers
Classifier: Topic :: Office/Business :: Scheduling
Classifier: License :: OSI Approved :: Apache Software License
Classifier: Programming Language :: Python
Classifier: Programming Language :: Python :: 3 :: Only
Classifier: Programming Language :: Python :: 3
Classifier: Programming Language :: Python :: 3.6
Classifier: Programming Language :: Python :: 3.7
Classifier: Programming Language :: Python :: 3.8
Classifier: Typing :: Typed
License-File: LICENSE.rst
